covalent_blueprints/__init__.py
covalent_blueprints/decorator.py
covalent_blueprints/logger.py
covalent_blueprints/blueprints/__init__.py
covalent_blueprints/blueprints/blueprints.py
covalent_blueprints/blueprints/executor_map.py
covalent_blueprints/blueprints/inputs.py
covalent_blueprints/blueprints/summary.py
covalent_blueprints/blueprints/utilities.py
covalent_blueprints/blueprints/templates/__init__.py
covalent_blueprints/blueprints/templates/single_service_deployment.py
covalent_blueprints/blueprints/templates/single_service_workflow.py
covalent_blueprints/reader/__init__.py
covalent_blueprints/reader/capture.py
covalent_blueprints/reader/script.py
covalent_blueprints/reader/utilities.py
tests/__init__.py
tests/test_calling_inside_and_outside_lattice.py
tests/test_get_blueprint.py
tests/samples/_scripts/_deploy_chatbot.py
covalent_blueprints-0.6.1.dist-info/LICENSE
covalent_blueprints-0.6.1.dist-info/METADATA
covalent_blueprints-0.6.1.dist-info/WHEEL
covalent_blueprints-0.6.1.dist-info/top_level.txt
covalent_blueprints-0.6.1.dist-info/RECORD
