Metadata-Version: 2.1
Name: covalent-blueprints
Version: 0.6.1
Summary: Covalent Blueprints: a toolkit for creating pre-packaged, reusable Covalent projects.
Author-email: Agnostiq <support@agnostiq.ai>
Maintainer-email: Ara Ghukasyan <ara@agnostiq.ai>, Sankalp Sanand <sankalp@agnostiq.ai>
License:                                  Apache License
Project-URL: Homepage, https://github.com/AgnostiqHQ/covalent-blueprints
Keywords: covalent,covalent-cloud,blueprints,agnostiq
Classifier: Development Status :: 1 - Planning
Classifier: Environment :: Console
Classifier: Environment :: Plugins
Classifier: Intended Audience :: Developers
Classifier: Intended Audience :: Education
Classifier: Intended Audience :: Science/Research
Classifier: License :: Other/Proprietary License
Classifier: Natural Language :: English
Classifier: Operating System :: MacOS
Classifier: Operating System :: POSIX :: Linux
Classifier: Programming Language :: Python :: 3
Classifier: Programming Language :: Python :: 3 :: Only
Classifier: Programming Language :: Python :: 3.8
Classifier: Programming Language :: Python :: 3.9
Classifier: Programming Language :: Python :: 3.10
Classifier: Topic :: Adaptive Technologies
Classifier: Topic :: Scientific/Engineering
Classifier: Topic :: Scientific/Engineering :: Interface Engine/Protocol Translator
Classifier: Topic :: Software Development
Classifier: Topic :: System :: Distributed Computing
Requires-Python: >=3.8
License-File: LICENSE
Requires-Dist: covalent-cloud>=0.81.0
